pylid/__init__.py
pylid-2019.10.16.8.44.1.324752.dist-info/LICENSE
pylid-2019.10.16.8.44.1.324752.dist-info/METADATA
pylid-2019.10.16.8.44.1.324752.dist-info/WHEEL
pylid-2019.10.16.8.44.1.324752.dist-info/top_level.txt
pylid-2019.10.16.8.44.1.324752.dist-info/RECORD
