Metadata-Version: 2.1
Name: pylid
Version: 2019.10.16.8.44.1.324752
Summary: pylid
Home-page: https://github.com/yehonadav/pylid
Author: yehonadav
Author-email: yonadav.barilan@gmail.com
License: apache-2.0
Platform: UNKNOWN
Classifier: Programming Language :: Python :: 3.7
